cosmo/.DS_Store
cosmo/README.md
cosmo/__init__.py
cosmo/cli/__init__.py
cosmo/cli/cli.py
cosmo/code_interpreters/.DS_Store
cosmo/code_interpreters/__init__.py
cosmo/code_interpreters/base_code_interpreter.py
cosmo/code_interpreters/create_code_interpreter.py
cosmo/code_interpreters/language_map.py
cosmo/code_interpreters/languages/__init__.py
cosmo/code_interpreters/languages/applescript.py
cosmo/code_interpreters/languages/html.py
cosmo/code_interpreters/languages/javascript.py
cosmo/code_interpreters/languages/powershell.py
cosmo/code_interpreters/languages/python.py
cosmo/code_interpreters/languages/r.py
cosmo/code_interpreters/languages/shell.py
cosmo/code_interpreters/subprocess_code_interpreter.py
cosmo/config.yaml
cosmo/core/__init__.py
cosmo/core/core.py
cosmo/core/generate_system_message.py
cosmo/core/respond.py
cosmo/llm/ARCHIVE_setup_local_text_llm.py
cosmo/llm/__init__.py
cosmo/llm/convert_to_coding_llm.py
cosmo/llm/setup_llm.py
cosmo/llm/setup_openai_coding_llm.py
cosmo/llm/setup_text_llm.py
cosmo/rag/ARCHIVE_local_get_relevant_procedures_string.py
cosmo/rag/__init__.py
cosmo/rag/get_relevant_procedures_string.py
cosmo/terminal_interface/.DS_Store
cosmo/terminal_interface/__init__.py
cosmo/terminal_interface/components/base_block.py
cosmo/terminal_interface/components/code_block.py
cosmo/terminal_interface/components/message_block.py
cosmo/terminal_interface/conversation_navigator.py
cosmo/terminal_interface/magic_commands.py
cosmo/terminal_interface/render_past_conversation.py
cosmo/terminal_interface/terminal_interface.py
cosmo/terminal_interface/validate_llm_settings.py
cosmo/utils/__init__.py
cosmo/utils/check_for_package.py
cosmo/utils/check_for_update.py
cosmo/utils/convert_to_openai_messages.py
cosmo/utils/count_tokens.py
cosmo/utils/display_markdown_message.py
cosmo/utils/embed.py
cosmo/utils/get_config.py
cosmo/utils/get_conversations.py
cosmo/utils/get_user_info_string.py
cosmo/utils/local_storage_path.py
cosmo/utils/merge_deltas.py
cosmoai-1.0.2.dist-info/LICENSE
cosmoai-1.0.2.dist-info/METADATA
cosmoai-1.0.2.dist-info/WHEEL
cosmoai-1.0.2.dist-info/entry_points.txt
cosmoai-1.0.2.dist-info/RECORD
